<annotation verified="yes">
	<folder>dataset_size_changed</folder>
	<filename>IMG_20200607_124113890_HDR.jpg</filename>
	<path>D:\PDG\Testing_Object_Detector\dataset_size_changed\training\IMG_20200607_124113890_HDR.jpg</path>
	<source>
		<database>Unknown</database>
	</source>
	<size>
		<width>1040</width>
		<height>1040</height>
		<depth>3</depth>
	</size>
	<segmented>0</segmented>
	<object>
		<name>ventilador</name>
		<pose>Unspecified</pose>
		<truncated>0</truncated>
		<difficult>0</difficult>
		<bndbox>
			<xmin>388</xmin>
			<ymin>494</ymin>
			<xmax>777</xmax>
			<ymax>1035</ymax>
		</bndbox>
	</object>
	<object>
		<name>ventilador</name>
		<pose>Unspecified</pose>
		<truncated>0</truncated>
		<difficult>0</difficult>
		<bndbox>
			<xmin>31</xmin>
			<ymin>483</ymin>
			<xmax>286</xmax>
			<ymax>999</ymax>
		</bndbox>
	</object>
	<object>
		<name>tv</name>
		<pose>Unspecified</pose>
		<truncated>0</truncated>
		<difficult>0</difficult>
		<bndbox>
			<xmin>488</xmin>
			<ymin>197</ymin>
			<xmax>786</xmax>
			<ymax>489</ymax>
		</bndbox>
	</object>
</annotation>
